nexuscli/__init__.py
nexuscli/exception.py
nexuscli/nexus_client.py
nexuscli/nexus_config.py
nexuscli/nexus_http.py
nexuscli/nexus_util.py
nexuscli/api/__init__.py
nexuscli/api/base_collection.py
nexuscli/api/base_model.py
nexuscli/api/util.py
nexuscli/api/validations.py
nexuscli/api/blobstore/__init__.py
nexuscli/api/blobstore/collection.py
nexuscli/api/blobstore/model.py
nexuscli/api/cleanup_policy/__init__.py
nexuscli/api/cleanup_policy/collection.py
nexuscli/api/cleanup_policy/model.py
nexuscli/api/repository/__init__.py
nexuscli/api/repository/collection.py
nexuscli/api/repository/model.py
nexuscli/api/repository/base_models/__init__.py
nexuscli/api/repository/base_models/base_repository.py
nexuscli/api/repository/base_models/group_repository.py
nexuscli/api/repository/base_models/hosted_repository.py
nexuscli/api/repository/base_models/proxy_repository.py
nexuscli/api/repository/base_models/repository.py
nexuscli/api/repository/base_models/util.py
nexuscli/api/repository/recipes/__init__.py
nexuscli/api/repository/recipes/apt.py
nexuscli/api/repository/recipes/bower.py
nexuscli/api/repository/recipes/docker.py
nexuscli/api/repository/recipes/maven.py
nexuscli/api/repository/recipes/npm.py
nexuscli/api/repository/recipes/nuget.py
nexuscli/api/repository/recipes/pypi.py
nexuscli/api/repository/recipes/raw.py
nexuscli/api/repository/recipes/rubygems.py
nexuscli/api/repository/recipes/validations.py
nexuscli/api/repository/recipes/yum.py
nexuscli/api/script/__init__.py
nexuscli/api/script/model.py
nexuscli/api/script/groovy/nexus3-cli-cleanup-policy.groovy
nexuscli/api/script/groovy/nexus3-cli-cleanup-policy_3.20.0.groovy
nexuscli/api/script/groovy/nexus3-cli-cleanup-policy_3.27.0.groovy
nexuscli/api/script/groovy/nexus3-cli-repository-create.groovy
nexuscli/api/script/groovy/nexus3-cli-repository-create_3.21.0.groovy
nexuscli/api/script/groovy/nexus3-cli-repository-delete.groovy
nexuscli/api/script/groovy/nexus3-cli-repository-get.groovy
nexus3_cli-4.2.1.dist-info/LICENSE
nexus3_cli-4.2.1.dist-info/METADATA
nexus3_cli-4.2.1.dist-info/WHEEL
nexus3_cli-4.2.1.dist-info/entry_points.txt
nexus3_cli-4.2.1.dist-info/top_level.txt
nexus3_cli-4.2.1.dist-info/RECORD
