Metadata-Version: 2.1
Name: nexus3-cli
Version: 4.2.1
Summary: A python-based CLI for Sonatype Nexus OSS 3
Home-page: https://gitlab.com/thiagocsf/nexus3-cli
Author: Thiago Figueiró
License: MIT
Platform: UNKNOWN
Classifier: Development Status :: 5 - Production/Stable
Classifier: Intended Audience :: Developers
Classifier: Intended Audience :: Information Technology
Classifier: Topic :: System :: Systems Administration
Classifier: Topic :: Utilities
Classifier: License :: OSI Approved :: MIT License
Classifier: Programming Language :: Python :: 3
Classifier: Programming Language :: Python :: 3.6
Classifier: Programming Language :: Python :: 3.7
Classifier: Programming Language :: Python :: 3.8
Requires-Python: >=3.6,<4
License-File: LICENSE
Requires-Dist: click <9,>=8.0.1
Requires-Dist: click-aliases <2,>=1.0.1
Requires-Dist: inflect <6,>=5.3.0
Requires-Dist: requests[security] <3,>=2.14.2
Requires-Dist: semver <3,>=2.10.1
Requires-Dist: texttable <2,>=1.6.2
Requires-Dist: twine <4,>=3.4.1
Provides-Extra: test
Requires-Dist: codecov ; extra == 'test'
Requires-Dist: flake8 ; extra == 'test'
Requires-Dist: pytest ; extra == 'test'
Requires-Dist: pytest-cov ; extra == 'test'
Requires-Dist: pytest-helpers-namespace ; extra == 'test'
Requires-Dist: pytest-mock ; extra == 'test'
Requires-Dist: pytest-faker ; extra == 'test'
